bitfield/__init__.py
bitfield/admin.py
bitfield/apps.py
bitfield/compat.py
bitfield/forms.py
bitfield/models.py
bitfield/query.py
bitfield/types.py
bitfield/tests/__init__.py
bitfield/tests/forms.py
bitfield/tests/models.py
bitfield/tests/tests.py
django_ivc_bitfield-1.9.7.dist-info/LICENSE
django_ivc_bitfield-1.9.7.dist-info/METADATA
django_ivc_bitfield-1.9.7.dist-info/WHEEL
django_ivc_bitfield-1.9.7.dist-info/top_level.txt
django_ivc_bitfield-1.9.7.dist-info/RECORD
