Metadata-Version: 2.1
Name: django-ivc-bitfield
Version: 1.9.7
Summary: BitField in Django
Home-page: https://github.com/ivc-inform/django-bitfield.git
Author: Disqus
Author-email: info@ivc-inform.ru
License: UNKNOWN
Platform: UNKNOWN
Classifier: Framework :: Django
Classifier: Intended Audience :: Developers
Classifier: Intended Audience :: System Administrators
Classifier: Operating System :: OS Independent
Classifier: Topic :: Software Development
Classifier: Programming Language :: Python
Classifier: Programming Language :: Python :: 3.6
Classifier: Programming Language :: Python :: 3.7
Classifier: Programming Language :: Python :: 3.8
Requires-Dist: Django (>=2.2)
Requires-Dist: six
Requires-Dist: psycopg2
Provides-Extra: tests
Requires-Dist: flake8 ; extra == 'tests'
Requires-Dist: mysqlclient ; extra == 'tests'
Requires-Dist: psycopg2 ; extra == 'tests'
Requires-Dist: pytest-django ; extra == 'tests'
